[
    {"title":"dangerously Set InnerHTML","desc":"先把这个想写很久的东西写进来","date":"2017.04.20","url":"dangerously"},
    {"title":"Object.assign()","desc":"Object.assign() 方法用于将所有可枚举的属性的值从一个或多个源对象复制到目标对象。它将返回目标对象。","date":"2017.04.22","url":"assign"},
    {"title":"A Beautiful MarkDown","desc":"Github MarkDown And Emoji","date":"2017.04.23","url":"lovemd"},
    {"title":"store action reducer redux-actions","desc":"来自一个渣渣的 react 项目使用 redux 时的困惑","date":"2017.04.23","url":"reduxTrouble"},
    {"title":"HTML标签的嵌套规则","desc":"就是要记录一下这个垃圾的问题","date":"2017.05.17","url":"tagNesting"},
    {"title":"百度地图 API 定位","desc":"只记录一下 React 项目中个人第一次使用的经历，百度开发者中心...走你","date":"2017.05.18","url":"baiduMapsAPI"},
    {"title":"css 超出部分省略号 单行,多行,模糊","desc":"单行文本超出部分省略号再熟悉不过，拓展延伸一下多行文本超出省略号以及模糊显示","date":"2017.05.22","url":"textOverflowEllipsis"},
    {"title":"css3实现超出文本指定行数与省略号效果","desc":"超出文本指定行数","date":"2017.08.10","url":"lineClamp"},
    {"title":"Create-React-App创建antd-mobile开发环境","desc":"使用Create-React-App脚手架搭建antd-mobile的开发环境","date":"2017.08.10","url":"createReactApp"},
    {"title":"React Router 4","desc":"React Router 4 的使用方法","date":"2017.08.13","url":"reactRouter4"},
    {"title":"微信小程序开发(一)","desc":"动态修改页面标题","date":"2017.08.24","url":"wechatAppTitle"},
    {"title":"关于svg","desc":"svg图标不能用img标签","date":"2017.09.20","url":"aboutSVG"},
    {"title":"momentJS","desc":"JavaScript 日期处理类库","date":"2017.11.28","url":"momentJS"},
    {"title":"商品SKU","desc":"电商后台管理商品规格","date":"2017.11.29","url":"goodsSKU"},
    {"title":"Array对象","desc":"数组对象的一些方法","date":"2017.11.29","url":"arrayObj"},
    {"title":"GitLab","desc":"GitLab 上把新的 commits 使用在自己的 fork 上","date":"2018.01.18","url":"gitlab"},
    {"title":"git","desc":"有关git的一些方法","date":"2018.01.23","url":"git"}
]
